{"@dcolfovalue": {"match": "dco lfo value", "value": 0.0, "index": 1}, "@dcopwmvalue": {"match": "dco pwm value", "value": 1.0, "index": 2}, "@dcopwmmode": {"match": "dco pwm mode", "value": 1.0, "index": 3}, "@dcopulseenabled": {"match": "dco pulse enabled", "value": 1.0, "index": 4}, "@dcosawenabled": {"match": "dco saw enabled", "value": 1.0, "index": 5}, "@dcosuboscenabled": {"match": "dco sub osc enabled", "value": 1.0, "index": 6}, "@dcosuboscvolume": {"match": "dco sub osc volume", "value": 1.0, "index": 7}, "@dconoisevolume": {"match": "dco noise volume", "value": 0.0, "index": 8}, "@filtercutoff": {"match": "filter cutoff", "value": 0.496000022, "index": 10}, "@filterresonance": {"match": "filter resonance", "value": 0.672000051, "index": 11}, "@filterenvelopemode": {"match": "filter env mode", "value": 0.0, "index": 12}, "@filterenvelopevalue": {"match": "filter env", "value": 0.0, "index": 13}, "@filtermodulationvalue": {"match": "filter modulation", "value": 0.0, "index": 14}, "@filterkeyboardvalue": {"match": "filter keyboard", "value": 1.0, "index": 15}, "@volume": {"match": "master volume", "value": 0.688000023, "index": 16}, "@masterfinetune": {"match": "master fine tune", "value": 0.5, "index": 17}, "@octavetranspose": {"match": "master octave transpose", "value": 0.668000042, "index": 18}, "@vcamode": {"match": "vca mode", "value": 1.0, "index": 19}, "@adsrattack": {"match": "attack", "value": 0.200000003, "index": 20}, "@adsrdecay": {"match": "decay", "value": 0.0, "index": 21}, "@adsrsustain": {"match": "sustain", "value": 1.0, "index": 22}, "@adsrrelease": {"match": "release", "value": 0.604000032, "index": 23}, "@lforate": {"match": "lfo rate", "value": 0.0, "index": 24}, "@lfodelaytime": {"match": "lfo delay", "value": 0.712000012, "index": 25}, "@lfotriggermode": {"match": "lfo trigger mode", "value": 0.556000054, "index": 26}, "@lfowaveform": {"match": "lfo waveform", "value": 0.0, "index": 29}, "@chorus1enable": {"match": "chorus 1", "value": 1.0, "index": 30}, "@chorus2enable": {"match": "chorus 2", "value": 0.0, "index": 31}, "@controlvelocityvolume": {"match": "control velocity volume", "value": 0.0, "index": 38}, "@controlvelocityenvelope": {"match": "control velocity envelope", "value": 0.0, "index": 39}, "@controlbenderfilter": {"match": "control pitch bend filter", "value": 0.0, "index": 40}, "@controlbenderdco": {"match": "control pitch bend dco", "value": 0.0, "index": 41}, "@portamentointensity": {"match": "portamento intensity", "value": 0.0, "index": 43}, "@portamentomode": {"match": "portamento mode", "value": 0.0, "index": 42}, "@arpenabled": {"match": "arp enabled", "value": 0.0, "index": 32}, "@arpsyncenabled": {"match": "arp sync enabled", "value": 0.0, "index": 33}, "@arpmode": {"match": "arp mode", "value": 0.444000036, "index": 34}, "@arprange": {"match": "arp range", "value": 0.519000053, "index": 35}, "@arprate": {"match": "arp rate", "value": 0.496000022, "index": 36}, "@voicehold": {"match": "voice hold", "value": 0.0, "index": 46}, "@miditriggerarp16sync": {"match": "trigger arp by midi channel 16", "value": 0.0, "index": 47}, "@midiclocksync": {"match": "clock sync", "value": 0.0, "index": 48}, "@hostsync": {"match": "host sync", "value": 0.0, "index": 49}, "@maxpoly": {"match": "max voices", "value": 0.454545468, "index": 50}, "@keytranspose": {"match": "keytranspose", "value": 0.5, "index": 51}, "@lfomanualtriggerenabled": {"match": "lfo trigger enabled", "value": 0.0, "index": 27}}